airship/__init__.py
airship/airship.py
airship/cleanbin.py
airship-1.5.6.dist-info/DESCRIPTION.rst
airship-1.5.6.dist-info/METADATA
airship-1.5.6.dist-info/RECORD
airship-1.5.6.dist-info/WHEEL
airship-1.5.6.dist-info/entry_points.txt
airship-1.5.6.dist-info/metadata.json
airship-1.5.6.dist-info/top_level.txt
